{
  "id": "08-sequential-design",
  "title": "স্টেট ডায়াগ্রাম, মিলি/মুর মেশিন ও স্টেট রিডাকশন",
  "type": "lesson",
  "estimatedMinutes": 22,
  "content": [
    {
      "type": "heading",
      "value": "সিকোয়েন্সিয়াল আচরণ মডেলিং"
    },
    {
      "type": "text",
      "value": "একটি সিকোয়েন্সিয়াল সার্কিটের সময়ের সাথে আচরণ একটি স্টেট ডায়াগ্রামে ধরা হয়: স্টেটগুলো বৃত্ত, এবং তীরগুলো (ইনপুট/আউটপুট লেবেলযুক্ত) প্রতিটি ক্লক এজে ট্রিগার হওয়া পরিবর্তন (transition) দেখায়।"
    },
    {
      "type": "heading",
      "value": "মুর মেশিন"
    },
    {
      "type": "text",
      "value": "আউটপুট শুধুমাত্র বর্তমান স্টেটের উপর নির্ভর করে, সরাসরি ইনপুটের উপর নয়। আউটপুটগুলো স্টেট বৃত্তের ভেতরে (বা সংযুক্ত করে) লেখা হয়।"
    },
    {
      "type": "heading",
      "value": "মিলি মেশিন"
    },
    {
      "type": "text",
      "value": "আউটপুট বর্তমান স্টেট ও বর্তমান ইনপুট উভয়ের উপর নির্ভর করে। আউটপুটগুলো ট্রানজিশন তীরের উপর লেখা হয়, স্টেটে নয়। মিলি মেশিন প্রায়ই সমতুল্য মুর মেশিনের চেয়ে এক ক্লক চক্র দ্রুত সাড়া দেয়, কিন্তু ইনপুট অ্যাসিনক্রোনাসভাবে পরিবর্তিত হলে এর আউটপুটে গ্লিচ হতে পারে।"
    },
    {
      "type": "heading",
      "value": "সিকোয়েন্সিয়াল সার্কিট ডিজাইন পদ্ধতি"
    },
    {
      "type": "list",
      "items": [
        "১. সমস্যার বর্ণনা থেকে স্টেট ডায়াগ্রাম তৈরি করুন",
        "২. স্টেট টেবিল তৈরি করুন (বর্তমান স্টেট, ইনপুট, পরবর্তী স্টেট, আউটপুট)",
        "৩. প্রতিটি স্টেটে বাইনারি কোড নির্ধারণ করুন",
        "৪. ফ্লিপ-ফ্লপ এক্সাইটেশন সমীকরণ ও আউটপুট সমীকরণ তৈরি করুন (প্রায়ই K-ম্যাপের মাধ্যমে)",
        "৫. ফলাফল লজিক সার্কিট আঁকুন"
      ]
    },
    {
      "type": "heading",
      "value": "স্টেট রিডাকশন"
    },
    {
      "type": "text",
      "value": "দুটি স্টেট সমতুল্য যদি, প্রতিটি সম্ভাব্য ইনপুটের জন্য, তারা একই আউটপুট তৈরি করে এবং সমতুল্য পরবর্তী স্টেটে স্থানান্তরিত হয়। সমতুল্য স্টেট একত্র করলে প্রয়োজনীয় মোট ফ্লিপ-ফ্লপের সংখ্যা কমে যায়, যা সার্কিটের বাহ্যিক আচরণ পরিবর্তন না করেই সার্কিটের খরচ কমায়।"
    },
    {
      "type": "heading",
      "value": "স্টেট অ্যাসাইনমেন্ট"
    },
    {
      "type": "text",
      "value": "অপ্রয়োজনীয় স্টেট সরিয়ে দেওয়ার পর, অবশিষ্ট প্রতিটি স্টেটে একটি অনন্য বাইনারি কোড নির্ধারণ করা হয়। ভিন্ন ভিন্ন অ্যাসাইনমেন্ট সার্কিটের জটিলতায় ব্যাপক পার্থক্য আনতে পারে, এ কারণেই এই ধাপটি একটি সচেতন ডিজাইন সিদ্ধান্ত, এলোমেলো নয়।"
    },
    {
      "type": "tip",
      "value": "স্টেট-রিডাকশন সমস্যা সমাধানের সময়, অনুমান না করে সমতুল্য স্টেট জোড়া পদ্ধতিগতভাবে খুঁজে বের করতে একটি ইমপ্লিকেশন টেবিল তৈরি করুন (অথবা শুধু স্টেট-টেবিল সারিগুলো জোড়ায় জোড়ায় তুলনা করুন)।"
    }
  ],
  "quiz": [
    {
      "question": "একটি মুর মেশিনে, আউটপুট কীসের উপর নির্ভর করে:",
      "options": [
        "শুধু বর্তমান ইনপুট",
        "শুধু বর্তমান স্টেট",
        "স্টেট ও ইনপুট উভয়ই"
      ],
      "answer": 1
    },
    {
      "question": "একটি মিলি মেশিনে, স্টেট ডায়াগ্রামে আউটপুট কোথায় লেবেল করা হয়?",
      "options": [
        "স্টেট বৃত্তগুলোর ভেতরে",
        "ট্রানজিশন তীরগুলোর উপর",
        "এগুলো কখনোই লেবেল করা হয় না"
      ],
      "answer": 1
    },
    {
      "question": "স্টেট রিডাকশন কেন করা হয়?",
      "options": [
        "আরও ফ্লিপ-ফ্লপ যোগ করতে",
        "সমতুল্য স্টেট একত্র করতে ও সার্কিটের খরচ কমাতে",
        "স্টেট ডায়াগ্রামকে আরও জটিল করতে"
      ],
      "answer": 1
    }
  ]
}